LianaiXingfuZhinan/README.md
LianaiXingfuZhinan/__init__.py
LianaiXingfuZhinan/__main__.py
LianaiXingfuZhinan/file.epub
LianaiXingfuZhinan/index.html
LianaiXingfuZhinan/css/__init__.py
LianaiXingfuZhinan/css/annotations.css
LianaiXingfuZhinan/css/main.css
LianaiXingfuZhinan/css/normalize.css
LianaiXingfuZhinan/css/popup.css
LianaiXingfuZhinan/font/__init__.py
LianaiXingfuZhinan/font/fontello.eot
LianaiXingfuZhinan/font/fontello.svg
LianaiXingfuZhinan/font/fontello.ttf
LianaiXingfuZhinan/font/fontello.woff
LianaiXingfuZhinan/img/__init__.py
LianaiXingfuZhinan/img/annotator-glyph-sprite.png
LianaiXingfuZhinan/img/annotator-icon-sprite.png
LianaiXingfuZhinan/img/apple-touch-icon.png
LianaiXingfuZhinan/img/cancelfullscreen.png
LianaiXingfuZhinan/img/close.png
LianaiXingfuZhinan/img/fullscreen.png
LianaiXingfuZhinan/img/loader.gif
LianaiXingfuZhinan/img/menu-icon.png
LianaiXingfuZhinan/img/save.png
LianaiXingfuZhinan/img/saved.png
LianaiXingfuZhinan/img/settings-s.png
LianaiXingfuZhinan/img/settings.png
LianaiXingfuZhinan/img/star.png
LianaiXingfuZhinan/js/__init__.py
LianaiXingfuZhinan/js/epub.js
LianaiXingfuZhinan/js/epub.min.js
LianaiXingfuZhinan/js/epub.min.map
LianaiXingfuZhinan/js/hooks.min.js
LianaiXingfuZhinan/js/hooks.min.map
LianaiXingfuZhinan/js/reader.js
LianaiXingfuZhinan/js/reader.js.map
LianaiXingfuZhinan/js/reader.min.js
LianaiXingfuZhinan/js/reader.min.map
LianaiXingfuZhinan/js/hooks/__init__.py
LianaiXingfuZhinan/js/hooks/extensions/__init__.py
LianaiXingfuZhinan/js/hooks/extensions/highlight.js
LianaiXingfuZhinan/js/libs/__init__.py
LianaiXingfuZhinan/js/libs/jquery.min.js
LianaiXingfuZhinan/js/libs/localforage.min.js
LianaiXingfuZhinan/js/libs/screenfull.js
LianaiXingfuZhinan/js/libs/screenfull.min.js
LianaiXingfuZhinan/js/libs/zip.min.js
LianaiXingfuZhinan/js/plugins/__init__.py
LianaiXingfuZhinan/js/plugins/hypothesis.js
LianaiXingfuZhinan/js/plugins/search.js
lianai_xingfu_zhinan-2022.10.11.0.dist-info/METADATA
lianai_xingfu_zhinan-2022.10.11.0.dist-info/WHEEL
lianai_xingfu_zhinan-2022.10.11.0.dist-info/entry_points.txt
lianai_xingfu_zhinan-2022.10.11.0.dist-info/top_level.txt
lianai_xingfu_zhinan-2022.10.11.0.dist-info/RECORD
